Metadata-Version: 2.1
Name: hofu
Version: 0.0.1
Summary: A simple library which implements higher order functions in python using functional chaining.
Home-page: https://github.com/Arthurdw/pyter
Author: Arthurdw <dev@arthurdw.com>
Classifier: Programming Language :: Python :: 3
Classifier: License :: OSI Approved :: MIT License
Classifier: Operating System :: OS Independent
Requires-Python: >=3.9
License-File: LICENSE
